[
    {
        "title": "The Lion King II: Simba's Pride",
        "date_x": "07/31/2000 ",
        "score": 69.0,
        "genre": [
            "Family",
            "Adventure",
            "Animation",
            "Action"
        ],
        "overview": "The circle of life continues for Simba, now fully grown and in his rightful place as the king of Pride Rock. Simba and Nala have given birth to a daughter, Kiara who's as rebellious as her father was. But Kiara drives her parents to distraction when she catches the eye of Kovu, the son of the evil lioness, Zira. Will Kovu steal Kiara's heart?",
        "actors": [
            "Matthew Broderick",
            "Simba (voice)",
            "Neve Campbell",
            "Kiara (voice)",
            "Jason Marsden",
            "Kovu (voice)",
            "Nathan Lane",
            "Timon (voice)",
            "Ernie Sabella",
            "Pumbaa (voice)",
            "Andy Dick",
            "Nuka (voice)",
            "Robert Guillaume",
            "Rafiki (voice)",
            "James Earl Jones",
            "Mufasa (voice)",
            "Moira Kelly",
            "Nala (voice)"
        ],
        "orig_title": "The Lion King II: Simba's Pride",
        "status": " Released",
        "orig_lang": " English",
        "budget_x": 140700000.0,
        "revenue": 490644301.8,
        "country": "AU"
    },
    {
        "title": "The Simpsons Movie",
        "date_x": "07/27/2007 ",
        "score": 70.0,
        "genre": [
            "Animation",
            "Comedy",
            "Family"
        ],
        "overview": "After Homer accidentally pollutes the town's water supply, Springfield is encased in a gigantic dome by the EPA and the Simpsons are declared fugitives.",
        "actors": [
            "Dan Castellaneta",
            "Homer Simpson / Itchy / Barney / Abe Simpson / Stage Manager / Krusty the Clown / Mayor Quimby / Mayor's Aide / Multi-Eyed Squirrel / Panicky Man / Sideshow Mel / Mr. Teeny / EPA Official / Kissing Cop / Bear / Boy on Phone / NSA Worker / Officer / Santa's Little Helper / Squeaky-Voiced Teen (voice)",
            "Julie Kavner",
            "Marge Simpson / Selma / Patty (voice)",
            "Nancy Cartwright",
            "Bart Simpson / Maggie Simpson / Ralph / Nelson / Todd Flanders / TV Daughter / Woman on Phone (voice)",
            "Yeardley Smith",
            "Lisa Simpson (voice)",
            "Hank Azaria",
            "Professor Frink / Comic Book Guy / Moe / Chief Wiggum / Lou / Carl / Cletus / Bumblebee Man / Male EPA Worker / Dome Depot Announcer / Kissing Cop / Carnival Barker / Counter Man / Apu / Drederick Tatum / Sea Captain / EPA Passenger / Robot / Dr. Nick / Wise Guy (voice)",
            "Harry Shearer",
            "Scratchy / Mr. Burns / Rev. Lovejoy / Ned Flanders / Lenny / Skull / President Arnold Schwarzenegger / Kent Brockman / Principal Skinner / Dr. Hibbert / Smithers / Toll Booth Man / Guard / Otto / Kang (voice)",
            "Pamela Hayden",
            "Milhouse Van Houten / Jimbo Jones / Rod Flanders (voice)",
            "Tress MacNeille",
            "Sweet Old Lady / Colin / Mrs. Skinner / Nelson's Mother / Pig / Cat Lady / Female EPA Worker / G.P.S. Woman / Cookie Kwan / Lindsey Naegle / TV Son / Medicine Woman / Girl on Phone (voice)",
            "Albert Brooks",
            "Russ Cargill (voice)"
        ],
        "orig_title": "The Simpsons Movie",
        "status": " Released",
        "orig_lang": " English",
        "budget_x": 72500000.0,
        "revenue": 527071022.0,
        "country": "AU"
    },
    {
        "title": "The Mummy Returns",
        "date_x": "05/10/2001 ",
        "score": 63.0,
        "genre": [
            "Adventure",
            "Action",
            "Fantasy"
        ],
        "overview": "Rick and Evelyn O’Connell, along with their 8-year-old son Alex, discover the key to the legendary Scorpion King’s might: the fabled Bracelet of Anubis. Unfortunately, a newly resurrected Imhotep has designs on the bracelet as well, and isn’t above kidnapping its new bearer, Alex, to gain control of Anubis’s otherworldly army.",
        "actors": [
            "Brendan Fraser",
            "Rick O'Connell",
            "Rachel Weisz",
            "Evelyn O'Connell / Nefertiri",
            "John Hannah",
            "Jonathan Carnahan",
            "Arnold Vosloo",
            "Imhotep",
            "Oded Fehr",
            "Ardeth Bay",
            "Patricia Velásquez",
            "Meela / Anck-Su-Namun",
            "Freddie Boath",
            "Alex O'Connell",
            "Alun Armstrong",
            "Baltus Hafez",
            "Dwayne Johnson",
            "Mathayus / The Scorpion King"
        ],
        "orig_title": "The Mummy Returns",
        "status": " Released",
        "orig_lang": " English",
        "budget_x": 98000000.0,
        "revenue": 435040395.0,
        "country": "AU"
    },
    {
        "title": "Elvis",
        "date_x": "06/23/2022 ",
        "score": 77.0,
        "genre": [
            "Drama",
            "Music",
            "History"
        ],
        "overview": "The life story of Elvis Presley as seen through the complicated relationship with his enigmatic manager, Colonel Tom Parker.",
        "actors": [
            "Austin Butler",
            "Elvis Presley",
            "Tom Hanks",
            "Colonel Tom Parker",
            "Olivia DeJonge",
            "Priscilla",
            "Helen Thomson",
            "Gladys Presley",
            "Richard Roxburgh",
            "Vernon Presley",
            "Kelvin Harrison Jr.",
            "B.B. King",
            "David Wenham",
            "Hank Snow",
            "Kodi Smit-McPhee",
            "Jimmie Rodgers Snow",
            "Luke Bracey",
            "Jerry Schilling"
        ],
        "orig_title": "Elvis",
        "status": " Released",
        "orig_lang": " English",
        "budget_x": 85000000.0,
        "revenue": 279854594.0,
        "country": "AU"
    },
    {
        "title": "The House",
        "date_x": "01/14/2022 ",
        "score": 71.0,
        "genre": [
            "Animation",
            "Drama",
            "Comedy",
            "Horror",
            "Fantasy"
        ],
        "overview": "Across different eras, a poor family, an anxious developer and a fed-up landlady become tied to the same mysterious house in this animated dark comedy.",
        "actors": [
            "Mia Goth",
            "Mabel (voice)",
            "Matthew Goode",
            "Raymond (voice)",
            "Claudie Blakley",
            "Penelope (voice)",
            "Eleanor De Swaef-Roels",
            "Isobel (voice)",
            "Mark Heap",
            "Mr. Thomas (voice)",
            "Stephanie Cole",
            "Great Aunt Eleanor (voice)",
            "Miranda Richardson",
            "Aunt Clarice (voice)",
            "David Peacock",
            "Uncle Lucien (voice)",
            "Barnaby Pilling",
            "Van Schoonbeek (voice)"
        ],
        "orig_title": "The House",
        "status": " Released",
        "orig_lang": " English",
        "budget_x": 40000000.0,
        "revenue": 31192425.0,
        "country": "GB"
    },
    {
        "title": "Fortress",
        "date_x": "03/01/2022 ",
        "score": 60.0,
        "genre": [
            "Action",
            "Thriller",
            "Crime"
        ],
        "overview": "The story revolves around a top-secret resort for retired U.S. intelligence officers. A group of criminals led by Balzary breach the compound, hellbent on revenge on Robert, forcing the retired officer and his son to save the day.",
        "actors": [
            "Jesse Metcalfe",
            "Paul",
            "Bruce Willis",
            "Robert",
            "Chad Michael Murray",
            "Balzary",
            "Kelly Greyson",
            "Kate",
            "Ser'Darius Blain",
            "Ulysses",
            "Katalina Viteri",
            "Sophia",
            "Shannen Doherty",
            "Dobbs",
            "Natalie Burn",
            "Sandra",
            "Kaleina Cordova",
            "Ava"
        ],
        "orig_title": "Fortress",
        "status": " Released",
        "orig_lang": " English",
        "budget_x": 12000000.0,
        "revenue": 46730578.0,
        "country": "AU"
    },
    {
        "title": "The Grandmother",
        "date_x": "04/06/2022 ",
        "score": 59.0,
        "genre": [
            "Drama",
            "Horror"
        ],
        "overview": "Susana leaves her life in Paris, where she works as a model, and returns to Madrid to take care of her grandmother Pilar.",
        "actors": [
            "Almudena Amor",
            "Susana",
            "Vera Valdez",
            "Pilar",
            "Karina Kolokolchykova",
            "Eva",
            "Marina Gutiérrez",
            "Adela",
            "Berta Sánchez",
            "Child Susana",
            "Alba Bonnin",
            "Child Eva",
            "Gabriela Calonfirescu",
            "Julita",
            "Ileana Wilson",
            "Doctor Romero",
            "Chacha Huang",
            "Burger Joint Waitress"
        ],
        "orig_title": " La abuela",
        "status": " Released",
        "orig_lang": " Spanish, Castilian",
        "budget_x": 3749231.0,
        "revenue": 1817696.0,
        "country": "FR"
    },
    {
        "title": "King of Kings",
        "date_x": "10/11/1961 ",
        "score": 71.0,
        "genre": [
            "Drama",
            "History"
        ],
        "overview": "Who is Jesus, and why does he impact all he meets? He is respected and reviled, emulated and accused, beloved, betrayed, and finally crucified. Yet that terrible fate would not be the end of the story.",
        "actors": [
            "Jeffrey Hunter",
            "Jesus",
            "Siobhán McKenna",
            "Mary",
            "Hurd Hatfield",
            "Pontius Pilate",
            "Ron Randell",
            "Lucius",
            "Viveca Lindfors",
            "Claudia",
            "Rita Gam",
            "Herodias",
            "Carmen Sevilla",
            "Mary Magdalene",
            "Brigid Bazlen",
            "Salome",
            "Harry Guardino",
            "Barabbas"
        ],
        "orig_title": "King of Kings",
        "status": " Released",
        "orig_lang": " English",
        "budget_x": 5037000.0,
        "revenue": 14483352.0,
        "country": "US"
    },
    {
        "title": "In Time",
        "date_x": "10/27/2011 ",
        "score": 70.0,
        "genre": [
            "Action",
            "Thriller",
            "Science Fiction"
        ],
        "overview": "In the not-too-distant future the aging gene has been switched off. To avoid overpopulation, time has become the currency and the way people pay for luxuries and necessities. The rich can live forever, while the rest try to negotiate for their immortality. A poor young man who comes into a fortune of time, though too late to help his mother from dying. He ends up on the run from a corrupt police force known as 'time keepers'.",
        "actors": [
            "Justin Timberlake",
            "Will Salas",
            "Amanda Seyfried",
            "Sylvia Weis",
            "Cillian Murphy",
            "Raymond Leon",
            "Olivia Wilde",
            "Rachel Salas",
            "Alex Pettyfer",
            "Fortis",
            "Johnny Galecki",
            "Borel",
            "Matt Bomer",
            "Henry Hamilton",
            "Vincent Kartheiser",
            "Philippe Weis",
            "Yaya DaCosta",
            "Greta"
        ],
        "orig_title": "In Time",
        "status": " Released",
        "orig_lang": " English",
        "budget_x": 35000000.0,
        "revenue": 165103952.0,
        "country": "AU"
    },
    {
        "title": "Hansan: Rising Dragon",
        "date_x": "08/05/2022 ",
        "score": 72.0,
        "genre": [
            "Action",
            "History",
            "Drama",
            "War"
        ],
        "overview": "In 1592, admiral Yi Sun-sin and his fleet face off against the might of the invading Japanese navy and its formidable warships. As the Korean forces fall into crisis, the admiral resorts to using his secret weapon, the dragon head ships known as geobukseon, in order to change the tide of this epic battle at sea.",
        "actors": [
            "Park Hae-il",
            "Admiral Yi Sun-shin",
            "Byun Yo-han",
            "Wakisaka Yasuharu",
            "Ahn Sung-ki",
            "Eo Yeong-dam",
            "Son Hyun-joo",
            "Won Gyun",
            "Kim Sung-kyu",
            "Junsa",
            "Kim Sung-kyun",
            "Kato Yoshiaki",
            "Kim Hyang-gi",
            "Jeong Bo-reum",
            "Ok Taec-yeon",
            "Im Jun-yeong",
            "Gong Myoung",
            "Yi Eok-gi"
        ],
        "orig_title": " 한산: 용의 출현",
        "status": " Released",
        "orig_lang": " Korean",
        "budget_x": 121000000.0,
        "revenue": 288842249.6,
        "country": "AU"
    },
    {
        "title": "Taken 3",
        "date_x": "01/08/2015 ",
        "score": 62.0,
        "genre": [
            "Thriller",
            "Action"
        ],
        "overview": "Ex-government operative Bryan Mills finds his life is shattered when he's falsely accused of a murder that hits close to home. As he's pursued by a savvy police inspector, Mills employs his particular set of skills to track the real killer and exact his unique brand of justice.",
        "actors": [
            "Liam Neeson",
            "Bryan Mills",
            "Forest Whitaker",
            "Inspector Franck Dotzler",
            "Famke Janssen",
            "Lenore Mills - St. John",
            "Maggie Grace",
            "Kim Mills",
            "Dougray Scott",
            "Stuart St. John",
            "Sam Spruell",
            "Oleg Malankov",
            "Don Harvey",
            "Garcia",
            "Dylan Bruno",
            "Smith",
            "Leland Orser",
            "Sam (Gilroy)"
        ],
        "orig_title": "Taken 3",
        "status": " Released",
        "orig_lang": " English",
        "budget_x": 48000000.0,
        "revenue": 327656424.0,
        "country": "AU"
    },
    {
        "title": "A Bug's Life",
        "date_x": "12/03/1998 ",
        "score": 70.0,
        "genre": [
            "Adventure",
            "Animation",
            "Comedy",
            "Family"
        ],
        "overview": "On behalf of \"oppressed bugs everywhere,\" an inventive ant named Flik hires a troupe of warrior bugs to defend his bustling colony from a horde of freeloading grasshoppers led by the evil-minded Hopper.",
        "actors": [
            "Dave Foley",
            "Flik (voice)",
            "Kevin Spacey",
            "Hopper (voice)",
            "Julia Louis-Dreyfus",
            "Atta (voice)",
            "Hayden Panettiere",
            "Dot (voice)",
            "Phyllis Diller",
            "Queen (voice)",
            "Richard Kind",
            "Molt (voice)",
            "David Hyde Pierce",
            "Slim (voice)",
            "Joe Ranft",
            "Heimlich (voice)",
            "Denis Leary",
            "Francis (voice)"
        ],
        "orig_title": "A Bug's Life",
        "status": " Released",
        "orig_lang": " English",
        "budget_x": 120000000.0,
        "revenue": 363258859.0,
        "country": "AU"
    },
    {
        "title": "Maleficent: Mistress of Evil",
        "date_x": "10/17/2019 ",
        "score": 73.0,
        "genre": [
            "Family",
            "Fantasy",
            "Adventure",
            "Action"
        ],
        "overview": "Maleficent and her goddaughter Aurora begin to question the complex family ties that bind them as they are pulled in different directions by impending nuptials, unexpected allies, and dark new forces at play.",
        "actors": [
            "Angelina Jolie",
            "Maleficent",
            "Elle Fanning",
            "Princess Aurora",
            "Harris Dickinson",
            "Prince Phillip",
            "Michelle Pfeiffer",
            "Queen Ingrith",
            "Sam Riley",
            "Diaval",
            "Chiwetel Ejiofor",
            "Conall",
            "Ed Skrein",
            "Borra",
            "Robert Lindsay",
            "King John",
            "David Gyasi",
            "Percival"
        ],
        "orig_title": "Maleficent: Mistress of Evil",
        "status": " Released",
        "orig_lang": " English",
        "budget_x": 185000000.0,
        "revenue": 489181357.0,
        "country": "AU"
    },
    {
        "title": "Bad Boys for Life",
        "date_x": "01/16/2020 ",
        "score": 72.0,
        "genre": [
            "Thriller",
            "Action",
            "Crime"
        ],
        "overview": "Marcus and Mike are forced to confront new threats, career changes, and midlife crises as they join the newly created elite team AMMO of the Miami police department to take down the ruthless Armando Armas, the vicious leader of a Miami drug cartel.",
        "actors": [
            "Will Smith",
            "Detective Mike Lowrey",
            "Martin Lawrence",
            "Detective Marcus Burnett",
            "Paola Nuñez",
            "Rita",
            "Vanessa Hudgens",
            "Kelly",
            "Alexander Ludwig",
            "Dorn",
            "Charles Melton",
            "Rafe",
            "Kate del Castillo",
            "Isabel",
            "Nicky Jam",
            "Zway-Lo",
            "Joe Pantoliano",
            "Captain Howard"
        ],
        "orig_title": "Bad Boys for Life",
        "status": " Released",
        "orig_lang": " English",
        "budget_x": 90000000.0,
        "revenue": 426505244.0,
        "country": "AU"
    },
    {
        "title": "Ready Player One",
        "date_x": "03/29/2018 ",
        "score": 76.0,
        "genre": [
            "Science Fiction",
            "Adventure",
            "Action"
        ],
        "overview": "When the creator of a popular video game system dies, a virtual contest is created to compete for his fortune.",
        "actors": [
            "Tye Sheridan",
            "Wade Watts / Parzival",
            "Olivia Cooke",
            "Samantha Cook / Artemis",
            "Ben Mendelsohn",
            "Nolan Sorrento",
            "Lena Waithe",
            "Helen Harris / Aech",
            "T.J. Miller",
            "i-R0k (voice)",
            "Simon Pegg",
            "Ogden Morrow",
            "Mark Rylance",
            "James Halliday / Anorak",
            "Philip Zhao",
            "Zhou / Sho",
            "Win Morisaki",
            "Toshiro / Daito"
        ],
        "orig_title": "Ready Player One",
        "status": " Released",
        "orig_lang": " English",
        "budget_x": 150000000.0,
        "revenue": 579055653.0,
        "country": "AU"
    },
    {
        "title": "The Second Coming of Christ",
        "date_x": "03/06/2018 ",
        "score": 36.0,
        "genre": [
            "Action",
            "Drama"
        ],
        "overview": "The journey of a woman scientist who, at the end of times, discovers that true Faith can bring Miracles.",
        "actors": [
            "Diana Angelson",
            "Dr. Beatrix Cera",
            "Jason London",
            "John Zachary",
            "Quinton Aaron",
            "Michael",
            "Sarah Bazler",
            "Olga",
            "Kurtis Anton",
            "Mike Bohen"
        ],
        "orig_title": "The Second Coming of Christ",
        "status": " Released",
        "orig_lang": " English",
        "budget_x": 47270000.0,
        "revenue": 329856760.8,
        "country": "US"
    },
    {
        "title": "The Flash",
        "date_x": "06/16/2023 ",
        "score": 0.0,
        "genre": [
            "Science Fiction",
            "Action",
            "Adventure"
        ],
        "overview": "The Flash travels through time to prevent the murder of his mother, but unwittingly causes changes that result in the creation of a multiverse.",
        "actors": [
            "Ezra Miller",
            "Barry Allen / The Flash",
            "Sasha Calle",
            "Kara Zor-El / Supergirl",
            "Michael Shannon",
            "General Zod",
            "Ron Livingston",
            "Henry Allen",
            "Maribel Verdú",
            "Nora Allen",
            "Kiersey Clemons",
            "Iris West",
            "Antje Traue",
            "Faora-Ul",
            "Michael Keaton",
            "Bruce Wayne / Batman",
            "Ben Affleck",
            "Bruce Wayne / Batman"
        ],
        "orig_title": "The Flash",
        "status": " Post Production",
        "orig_lang": " English",
        "budget_x": 200000000.0,
        "revenue": 1240261.6,
        "country": "US"
    },
    {
        "title": "The Chalk Line",
        "date_x": "09/09/2022 ",
        "score": 64.0,
        "genre": [
            "Horror"
        ],
        "overview": "After a couple finds a traumatized child of unknown origins, wife Paula must decipher the girl's strange behaviors to unlock her identity and dark past.",
        "actors": [
            "Elena Anaya",
            "Paula",
            "Pablo Molinero",
            "Simón",
            "Carlos Santos",
            "Eduardo",
            "Eva Llorach",
            "Maite",
            "Esther Acebo",
            "Claudia",
            "Tara Linke",
            "Ingrid's mother",
            "Eloy Azorín",
            "Beltrán",
            "Eva Tennear",
            "Clara",
            "Mona Martínez",
            "Sargento Arana"
        ],
        "orig_title": " Jaula",
        "status": " Released",
        "orig_lang": " Spanish, Castilian",
        "budget_x": 92600000.0,
        "revenue": 353391998.4,
        "country": "ES"
    },
    {
        "title": "Pokemon the Movie: Mewtwo Strikes Back - Evolution",
        "date_x": "07/12/2019 ",
        "score": 67.0,
        "genre": [
            "Animation",
            "Adventure",
            "Fantasy",
            "Action",
            "Family"
        ],
        "overview": "After accepting an invitation from a mysterious trainer, Ash, Misty and Brock meet Mewtwo, an artificially created Pokémon who wants to do battle.",
        "actors": [
            "Rica Matsumoto",
            "Satoshi (voice)",
            "Ikue Otani",
            "Pikachu (voice)",
            "Mayumi Iizuka",
            "Kasumi (voice)",
            "Satomi Korogi",
            "Togepi (voice)",
            "Yuji Ueda",
            "Takeshi (voice)",
            "Megumi Hayashibara",
            "Musashi (voice)",
            "Shin-ichiro Miki",
            "Kojiro (voice)",
            "Inuko Inuyama",
            "Nyarth (voice)",
            "Chika Fujimura",
            "Joy (voice)"
        ],
        "orig_title": " ミュウツーの逆襲 EVOLUTION",
        "status": " Released",
        "orig_lang": " Japanese",
        "budget_x": 59844080.0,
        "revenue": 26654184.0,
        "country": "JP"
    },
    {
        "title": "The Lost Lotteries",
        "date_x": "11/16/2022 ",
        "score": 60.0,
        "genre": [
            "Crime",
            "Comedy"
        ],
        "overview": "Five down-on-their-luck strangers must band together to steal back winning lottery tickets worth millions from a wicked mafia boss.",
        "actors": [
            "Wongravee Nateetorn",
            "Tay",
            "Phantira Pipityakorn",
            "Beat",
            "Padung Songsang",
            "Wen",
            "Napapa Tantrakul",
            "Zoe",
            "Somjit Jongjohor",
            "Khung",
            "Thanaporn Wagprayoon",
            "Toi",
            "Torpong Kul-On",
            "Mee",
            "Somyos Matures",
            "Doe",
            "Sutthirak Subvijitra",
            "Sek"
        ],
        "orig_title": " ปฏิบัติการกู้หวย",
        "status": " Released",
        "orig_lang": " Thai",
        "budget_x": 62800000.0,
        "revenue": 566738520.0,
        "country": "TH"
    },
    {
        "title": "November",
        "date_x": "05/11/2023 ",
        "score": 73.0,
        "genre": [
            "Thriller",
            "Crime",
            "Drama"
        ],
        "overview": "In November 2015, a series of unprecedented and deadly attacks hits Paris. The anti-terrorist police led by Heloise and her chief commander Fred - face an unprecedented level of pressure: in a race against the clock, they must find the perpetrators of the attacks as quickly as possible before they can strike again, travelling across Europe and beyond in one of the biggest manhunts in history.",
        "actors": [
            "Jean Dujardin",
            "Fred",
            "Anaïs Demoustier",
            "Inès",
            "Sandrine Kiberlain",
            "Héloïse",
            "Jérémie Renier",
            "Marco",
            "Lyna Khoudri",
            "Samia",
            "Cédric Kahn",
            "Martin",
            "Sofian Khammes",
            "Foued",
            "Sami Outalbali",
            "Kader",
            "Stéphane Bak",
            "Djibril"
        ],
        "orig_title": " Novembre",
        "status": " Released",
        "orig_lang": " French",
        "budget_x": 250000.0,
        "revenue": 191862.0,
        "country": "AU"
    },
    {
        "title": "The Nun 2",
        "date_x": "09/08/2023 ",
        "score": 0.0,
        "genre": [
            "Horror",
            "Mystery"
        ],
        "overview": "1956, France. A priest is murdered, an evil is spreading, and Sister Irene once again comes face to face with the malevolent force of Valak, the demon nun.",
        "actors": [
            "Taissa Farmiga",
            "Sister Irene",
            "Bonnie Aarons",
            "The Nun / Valak",
            "Storm Reid",
            "",
            "Jonas Bloquet",
            "Maurice Theriault",
            "Anna Popplewell",
            "Marcella",
            "Katelyn Rose Downey",
            "Sophie"
        ],
        "orig_title": "The Nun 2",
        "status": " In Production",
        "orig_lang": " English",
        "budget_x": 246000000.0,
        "revenue": 175269998.8,
        "country": "US"
    },
    {
        "title": "Aria the Benedizione",
        "date_x": "12/03/2021 ",
        "score": 63.0,
        "genre": [
            "Animation",
            "Comedy",
            "Science Fiction",
            "Fantasy"
        ],
        "overview": "Neo-Venezia has reached a long winter. Ai, Azusa and Anya, who were practicing jointly in the cold weather, visit the Undine Museum, led by Akira who seems not her usual self. At the museum, the trio meet its director, Asuka who is Akira's senior known as Himeya's legendary undine. The two of them are the successors to a gondola that has been carefully passed down since the founding of Himeya Company. However, Akira reveals that Aika, who is expected to inherit the gondola, has no intention of doing so. Azusa, who is not convinced, tries to find out why.",
        "actors": [
            "Junko Minagawa",
            "Akira E. Ferrari (voice)",
            "Chiwa Saito",
            "Aika S. Granzchesta (voice)",
            "Sayaka Ohara",
            "Alicia Florence (voice)",
            "Erino Hazuki",
            "Akari Mizunashi (voice)",
            "Ryo Hirohashi",
            "Alice Carroll (voice)",
            "Mai Nakahara",
            "Azusa B. McLaren (voice) / Guest B (voice)",
            "Kaori Mizuhashi",
            "Ai Aino (voice) / Hime M. Granzchesta (voice)",
            "Chinami Nishimura",
            "Aria Pokoteng (voice)",
            "Rina Sato",
            "Athena Glory (voice)"
        ],
        "orig_title": " ARIA The BENEDIZIONE",
        "status": " Released",
        "orig_lang": " Japanese",
        "budget_x": 184000000.0,
        "revenue": 428723514.8,
        "country": "JP"
    },
    {
        "title": "Sausage Party",
        "date_x": "08/11/2016 ",
        "score": 57.0,
        "genre": [
            "Adventure",
            "Animation",
            "Comedy",
            "Fantasy"
        ],
        "overview": "Frank leads a group of supermarket products on a quest to discover the truth about their existence and what really happens when they become chosen to leave the grocery store.",
        "actors": [
            "Seth Rogen",
            "Frank / Sergeant Pepper (voice)",
            "Kristen Wiig",
            "Brenda (voice)",
            "Jonah Hill",
            "Carl (voice)",
            "Bill Hader",
            "Firewater / Tequila / El Guaco (voice)",
            "Michael Cera",
            "Barry (voice)",
            "James Franco",
            "Druggie (voice)",
            "Danny McBride",
            "Honey Mustard (voice)",
            "Craig Robinson",
            "Grits (voice)",
            "Paul Rudd",
            "Darren (voice)"
        ],
        "orig_title": "Sausage Party",
        "status": " Released",
        "orig_lang": " English",
        "budget_x": 19000000.0,
        "revenue": 141344255.0,
        "country": "AU"
    },
    {
        "title": "Fortress: Sniper's Eye",
        "date_x": "04/29/2022 ",
        "score": 56.0,
        "genre": [
            "Action",
            "Thriller",
            "Crime"
        ],
        "overview": "Weeks after the deadly assault on Fortress Camp, Robert makes a daring rescue to save Sasha, the widow of his old nemesis Balzary. But back in the camp's command bunker, it appears Sasha may have devious plans of her own. As a new attack breaks out, Robert is confronted with a familiar face he thought he'd never see again…",
        "actors": [
            "Chad Michael Murray",
            "Balzary",
            "Bruce Willis",
            "Robert",
            "Jesse Metcalfe",
            "Paul",
            "Kelly Greyson",
            "Kate",
            "Ser'Darius Blain",
            "Ulysses",
            "Michael Sirow",
            "Ken Blain",
            "Welker White",
            "Carole",
            "Natali Yura",
            "Sasha",
            "Celeste Fianna",
            "Annette"
        ],
        "orig_title": "Fortress: Sniper's Eye",
        "status": " Released",
        "orig_lang": " English",
        "budget_x": 125600000.0,
        "revenue": 403087774.0,
        "country": "US"
    },
    {
        "title": "Fight Club",
        "date_x": "11/11/1999 ",
        "score": 84.0,
        "genre": [
            "Drama",
            "Thriller",
            "Comedy"
        ],
        "overview": "A ticking-time-bomb insomniac and a slippery soap salesman channel primal male aggression into a shocking new form of therapy. Their concept catches on, with underground \"fight clubs\" forming in every town, until an eccentric gets in the way and ignites an out-of-control spiral toward oblivion.",
        "actors": [
            "Edward Norton",
            "The Narrator",
            "Brad Pitt",
            "Tyler Durden",
            "Helena Bonham Carter",
            "Marla Singer",
            "Meat Loaf",
            "Robert \"Bob\" Paulson",
            "Jared Leto",
            "Angel Face",
            "Zach Grenier",
            "Richard Chesler",
            "Holt McCallany",
            "The Mechanic",
            "Eion Bailey",
            "Ricky",
            "Richmond Arquette",
            "Intern"
        ],
        "orig_title": "Fight Club",
        "status": " Released",
        "orig_lang": " English",
        "budget_x": 65000000.0,
        "revenue": 100820947.0,
        "country": "AU"
    },
    {
        "title": "Hercules",
        "date_x": "09/18/1997 ",
        "score": 75.0,
        "genre": [
            "Animation",
            "Family",
            "Fantasy",
            "Adventure",
            "Comedy",
            "Romance"
        ],
        "overview": "Bestowed with superhuman strength, a young mortal named Hercules sets out to prove himself a hero in the eyes of his father, the great god Zeus. Along with his friends Pegasus, a flying horse, and Phil, a personal trainer, Hercules is tricked by the hilarious, hotheaded villain Hades, who's plotting to take over Mount Olympus!",
        "actors": [
            "Tate Donovan",
            "Hercules (voice)",
            "Josh Keaton",
            "Young Hercules (voice)",
            "Roger Bart",
            "Young Hercules (singing voice)",
            "Danny DeVito",
            "Philoctetes (voice)",
            "James Woods",
            "Hades (voice)",
            "Susan Egan",
            "Meg (voice)",
            "Bobcat Goldthwait",
            "Pain (voice)",
            "Matt Frewer",
            "Panic (voice)",
            "Rip Torn",
            "Zeus (voice)"
        ],
        "orig_title": "Hercules",
        "status": " Released",
        "orig_lang": " English",
        "budget_x": 100000000.0,
        "revenue": 243388614.0,
        "country": "AU"
    },
    {
        "title": "Hercules",
        "date_x": "09/18/1997 ",
        "score": 75.0,
        "genre": [
            "Animation",
            "Family",
            "Fantasy",
            "Adventure",
            "Comedy",
            "Romance"
        ],
        "overview": "Bestowed with superhuman strength, a young mortal named Hercules sets out to prove himself a hero in the eyes of his father, the great god Zeus. Along with his friends Pegasus, a flying horse, and Phil, a personal trainer, Hercules is tricked by the hilarious, hotheaded villain Hades, who's plotting to take over Mount Olympus!",
        "actors": [
            "Tate Donovan",
            "Hercules (voice)",
            "Josh Keaton",
            "Young Hercules (voice)",
            "Roger Bart",
            "Young Hercules (singing voice)",
            "Danny DeVito",
            "Philoctetes (voice)",
            "James Woods",
            "Hades (voice)",
            "Susan Egan",
            "Meg (voice)",
            "Bobcat Goldthwait",
            "Pain (voice)",
            "Matt Frewer",
            "Panic (voice)",
            "Rip Torn",
            "Zeus (voice)"
        ],
        "orig_title": "Hercules",
        "status": " Released",
        "orig_lang": " English",
        "budget_x": 70000000.0,
        "revenue": 250700000.0,
        "country": "AU"
    },
    {
        "title": "Waktu Maghrib",
        "date_x": "02/09/2023 ",
        "score": 63.0,
        "genre": [
            "Horror"
        ],
        "overview": "The cruel terror chased the souls of Adi and Saman until. Ayu knows the reason for the terror. There is a sin that is committed at the most dangerous time, Maghrib Time. What sin did they commit? What happened to Adi, Saman, Ayu and the villagers?",
        "actors": [
            "Aulia Sarah",
            "Bu Woro",
            "Ali Fikry",
            "Adi",
            "Nafiza Fatia Rani",
            "Ayu",
            "Taskya Namya",
            "Ningsih",
            "Sadana Agung",
            "Hansip",
            "Bimasena",
            "Saman",
            "Kevin Abani",
            "Samiun",
            "Andri Mashadi",
            "Karta",
            "Muhammad Abe Baasyin",
            "Lurah"
        ],
        "orig_title": "Waktu Maghrib",
        "status": " Released",
        "orig_lang": " Indonesian",
        "budget_x": 87000000.0,
        "revenue": 476680473.8,
        "country": "ID"
    },
    {
        "title": "Legion",
        "date_x": "06/03/2010 ",
        "score": 58.0,
        "genre": [
            "Horror",
            "Action",
            "Fantasy"
        ],
        "overview": "When God loses faith in humankind, he sends his legion of angels to bring on the Apocalypse. Humanity's only hope for survival lies in a group of strangers trapped in an out-of-the-way, desert diner with the Archangel Michael.",
        "actors": [
            "Paul Bettany",
            "Michael",
            "Dennis Quaid",
            "Bob Hanson",
            "Lucas Black",
            "Jeep Hanson",
            "Kate Walsh",
            "Sandra Anderson",
            "Tyrese Gibson",
            "Kyle Williams",
            "Adrianne Palicki",
            "Charlie",
            "Willa Holland",
            "Audrey Anderson",
            "Charles S. Dutton",
            "Percy Walker",
            "Jon Tenney",
            "Howard Anderson"
        ],
        "orig_title": "Legion",
        "status": " Released",
        "orig_lang": " English",
        "budget_x": 26000000.0,
        "revenue": 67647574.0,
        "country": "AU"
    },
    {
        "title": "Six Swedish Girls in a Boarding School",
        "date_x": "09/28/1979 ",
        "score": 54.0,
        "genre": [
            "Comedy"
        ],
        "overview": "Miss Klein runs a boarding-school. The girls that go there are really \"free spirited.\" They chloroform a peeping Tom, lock two plumbers in the dormitories, strip for a gamekeeper and tease their gym teacher. In class, their biology teacher gets carried away while giving a demonstration of sex positions with the gym teacher. In the meantime, one of the girls makes some exciting alterations to their bicycles to make their rides more enjoyable.",
        "actors": [
            "Brigitte Lahaie",
            "Greta",
            "Nadine Pascal",
            "Inga",
            "Anne Libert",
            "Fräulein Stein",
            "France Lomay",
            "Kerstin",
            "Roman Huber",
            "Voyeur",
            "Danièle Troeger",
            "Lil",
            "Kathleen Kane",
            "Astrid",
            "Elsa Maroussia",
            "Selma",
            "Diane Kelly",
            "Marie-France"
        ],
        "orig_title": " Sechs Schwedinnen im Pensionat",
        "status": " Released",
        "orig_lang": " German",
        "budget_x": 76000000.0,
        "revenue": 152911218.6,
        "country": "DE"
    },
    {
        "title": "From Straight A's to XXX",
        "date_x": "02/11/2017 ",
        "score": 60.0,
        "genre": [
            "Drama",
            "TV Movie"
        ],
        "overview": "When a change of circumstances leaves Miriam unable to pay her college tuition, she makes a surprising decision: to start performing in adult films, using the pseudonym Belle Knox. Miriam lies to her family and her friends at school, keeping her double life a secret. But soon rumours spread and Miriam becomes the subject of vicious online attacks and unwanted attention. Miriam fights back: she talks to the media, saying her new line of work empowers her as a feminist. But her confident stand has unintended consequences. Miriam is shunned by her conservative family and her colleagues in the adult film world. One impulsive decision has quickly spiralled out of control - and Miriam's problems are just beginning.",
        "actors": [
            "Haley Pullos",
            "Miriam Weeks",
            "Sasha Clements",
            "Jolie",
            "Judd Nelson",
            "Don",
            "Alyson Bath",
            "Dora",
            "Jacky Lai",
            "Amy",
            "Jessica Lu",
            "Amanda",
            "Rachelle Gillis",
            "Jen",
            "Sarah Porchetta",
            "Roxy",
            "Imali Perera",
            "Mrs. Harcharan Weeks"
        ],
        "orig_title": "From Straight A's to XXX",
        "status": " Released",
        "orig_lang": " English",
        "budget_x": 127200000.0,
        "revenue": 410122022.6,
        "country": "US"
    },
    {
        "title": "Justice League",
        "date_x": "11/16/2017 ",
        "score": 61.0,
        "genre": [
            "Action",
            "Adventure",
            "Science Fiction"
        ],
        "overview": "Fuelled by his restored faith in humanity and inspired by Superman's selfless act, Bruce Wayne and Diana Prince assemble a team of metahumans consisting of Barry Allen, Arthur Curry and Victor Stone to face the catastrophic threat of Steppenwolf and the Parademons who are on the hunt for three Mother Boxes on Earth.",
        "actors": [
            "Ben Affleck",
            "Batman / Bruce Wayne",
            "Henry Cavill",
            "Superman / Clark Kent /  Kal-El",
            "Amy Adams",
            "Lois Lane",
            "Gal Gadot",
            "Wonder Woman / Diana Prince",
            "Ezra Miller",
            "The Flash / Barry Allen",
            "Jason Momoa",
            "Aquaman / Arthur Curry",
            "Ray Fisher",
            "Cyborg / Victor Stone",
            "Jeremy Irons",
            "Alfred Pennyworth",
            "Diane Lane",
            "Martha Kent"
        ],
        "orig_title": "Justice League",
        "status": " Released",
        "orig_lang": " English",
        "budget_x": 300000000.0,
        "revenue": 655945209.0,
        "country": "AU"
    },
    {
        "title": "The Last Temptation of Christ",
        "date_x": "10/13/1988 ",
        "score": 72.0,
        "genre": [
            "Drama"
        ],
        "overview": "Jesus, a humble Judean carpenter beginning to see that he is the son of God, is drawn into revolutionary action against the Roman occupiers by Judas -- despite his protestations that love, not violence, is the path to salvation. The burden of being the savior of mankind torments Jesus throughout his life, leading him to doubt.",
        "actors": [
            "Willem Dafoe",
            "Jesus",
            "Harvey Keitel",
            "Judas Iscariot",
            "Barbara Hershey",
            "Mary Magdalene",
            "Harry Dean Stanton",
            "Paulus",
            "David Bowie",
            "Pontius Pilatus",
            "Steve Shill",
            "Centurian",
            "Verna Bloom",
            "Mary",
            "Mother of Jesus",
            "Paul Greco",
            "Zealot",
            "Roberts Blossom",
            "Aged Master"
        ],
        "orig_title": "The Last Temptation of Christ",
        "status": " Released",
        "orig_lang": " English",
        "budget_x": 7000000.0,
        "revenue": 8373585.0,
        "country": "AU"
    },
    {
        "title": "Ron's Gone Wrong",
        "date_x": "10/21/2021 ",
        "score": 80.0,
        "genre": [
            "Animation",
            "Science Fiction",
            "Family",
            "Comedy"
        ],
        "overview": "In a world where walking, talking, digitally connected bots have become children's best friends, an 11-year-old finds that his robot buddy doesn't quite work the same as the others do.",
        "actors": [
            "Zach Galifianakis",
            "Ron (voice)",
            "Jack Dylan Grazer",
            "Barney (voice)",
            "Ed Helms",
            "Graham (voice)",
            "Olivia Colman",
            "Donka (voice)",
            "Justice Smith",
            "Marc (voice)",
            "Rob Delaney",
            "Andrew (voice)",
            "Kylie Cantrall",
            "Savannah (voice)",
            "Ricardo Hurtado",
            "Rich (voice)",
            "Marcus Scribner",
            "Alex (voice)"
        ],
        "orig_title": "Ron's Gone Wrong",
        "status": " Released",
        "orig_lang": " English",
        "budget_x": 30511197.0,
        "revenue": 60692022.0,
        "country": "AU"
    },
    {
        "title": "Mad Max: Fury Road",
        "date_x": "05/14/2015 ",
        "score": 76.0,
        "genre": [
            "Action",
            "Adventure",
            "Science Fiction"
        ],
        "overview": "An apocalyptic story set in the furthest reaches of our planet, in a stark desert landscape where humanity is broken, and most everyone is crazed fighting for the necessities of life. Within this world exist two rebels on the run who just might be able to restore order.",
        "actors": [
            "Tom Hardy",
            "Max Rockatansky",
            "Charlize Theron",
            "Imperator Furiosa",
            "Nicholas Hoult",
            "Nux",
            "Hugh Keays-Byrne",
            "Immortan Joe",
            "Riley Keough",
            "Capable",
            "Zoë Kravitz",
            "Toast the Knowing",
            "Rosie Huntington-Whiteley",
            "The Splendid Angharad",
            "Abbey Lee",
            "The Dag",
            "Courtney Eaton",
            "Cheedo the Fragile"
        ],
        "orig_title": "Mad Max: Fury Road",
        "status": " Released",
        "orig_lang": " English",
        "budget_x": 150000000.0,
        "revenue": 365769378.0,
        "country": "AU"
    },
    {
        "title": "How to Train Your Dragon 2",
        "date_x": "06/09/2014 ",
        "score": 77.0,
        "genre": [
            "Fantasy",
            "Action",
            "Adventure",
            "Animation",
            "Comedy",
            "Family"
        ],
        "overview": "Five years have passed since Hiccup and Toothless united the dragons and Vikings of Berk. Now, they spend their time charting unmapped territories. During one of their adventures, the pair discover a secret cave that houses hundreds of wild dragons -- and a mysterious dragon rider who turns out to be Hiccup's mother, Valka. Hiccup and Toothless then find themselves at the center of a battle to protect Berk from a power-hungry warrior named Drago.",
        "actors": [
            "Jay Baruchel",
            "Hiccup (voice)",
            "Cate Blanchett",
            "Valka (voice)",
            "Gerard Butler",
            "Stoick (voice)",
            "Craig Ferguson",
            "Gobber (voice)",
            "America Ferrera",
            "Astrid (voice)",
            "Jonah Hill",
            "Snotlout (voice)",
            "Christopher Mintz-Plasse",
            "Fishlegs (voice)",
            "T.J. Miller",
            "Tuffnut (voice)",
            "Kristen Wiig",
            "Ruffnut (voice)"
        ],
        "orig_title": "How to Train Your Dragon 2",
        "status": " Released",
        "orig_lang": " English",
        "budget_x": 145000000.0,
        "revenue": 614586270.0,
        "country": "AU"
    },
    {
        "title": "Blackout",
        "date_x": "10/12/2022 ",
        "score": 54.0,
        "genre": [
            "Action",
            "Adventure",
            "Thriller"
        ],
        "overview": "A man wakes in a hospital with no memory, and quickly finds himself on the run in a locked down hospital with the Cartel on his tail.",
        "actors": [
            "Josh Duhamel",
            "Cain",
            "Abbie Cornish",
            "Anna",
            "Omar Chaparro",
            "Eddie",
            "Nick Nolte",
            "Ethan McCoy",
            "Lou Ferrigno Jr.",
            "Agent Jackson Jacobs",
            "Bárbara de Regil",
            "Jenny",
            "Robert Dobson",
            "DEA Agent",
            "Pedro López",
            "The General",
            "Edison Ruiz",
            "Miguel"
        ],
        "orig_title": "Blackout",
        "status": " Released",
        "orig_lang": " English",
        "budget_x": 96400000.0,
        "revenue": 440151954.6,
        "country": "DK"
    },
    {
        "title": "Despicable Me",
        "date_x": "09/09/2010 ",
        "score": 72.0,
        "genre": [
            "Family",
            "Animation",
            "Comedy",
            "Crime"
        ],
        "overview": "Villainous Gru lives up to his reputation as a despicable, deplorable and downright unlikable guy when he hatches a plan to steal the moon from the sky. But he has a tough time staying on task after three orphans land in his care.",
        "actors": [
            "Steve Carell",
            "Gru (voice)",
            "Miranda Cosgrove",
            "Margo (voice)",
            "Dana Gaier",
            "Edith (voice)",
            "Elsie Fisher",
            "Agnes (voice)",
            "Jason Segel",
            "Vector (voice)",
            "Russell Brand",
            "Dr. Nefario (voice)",
            "Julie Andrews",
            "Gru's Mother (voice)",
            "Will Arnett",
            "Mr. Perkins (voice)",
            "Kristen Wiig",
            "Miss Hattie (voice)"
        ],
        "orig_title": "Despicable Me",
        "status": " Released",
        "orig_lang": " English",
        "budget_x": 69000000.0,
        "revenue": 543464573.0,
        "country": "AU"
    },
    {
        "title": "Lies My Sister Told Me",
        "date_x": "05/29/2022 ",
        "score": 66.0,
        "genre": [
            "TV Movie",
            "Thriller",
            "Drama"
        ],
        "overview": "A woman escapes from a mental hospital, intent on getting back the life she thinks was stolen from her by her twin sister. Instead, she walks into her worst nightmare.",
        "actors": [
            "Nicole Marie Johnson",
            "Jennifer / Tracy",
            "Kate Edmonds",
            "Layla",
            "Dominick Ficco",
            "Rob",
            "Scout Smith",
            "Karen",
            "Jonathan Stoddard",
            "Chad",
            "Emerson Niemchick",
            "Peter",
            "Ashley Sevier",
            "Head Nurse",
            "Britton Webb",
            "E.R. Doctor"
        ],
        "orig_title": "Lies My Sister Told Me",
        "status": " Released",
        "orig_lang": " English",
        "budget_x": 83800000.0,
        "revenue": 700431681.6,
        "country": "US"
    },
    {
        "title": "Ava",
        "date_x": "06/21/2017 ",
        "score": 62.0,
        "genre": [
            "Drama"
        ],
        "overview": "Ava, 13, is spending the summer on the Atlantic coast when she learns that she will lose her sight sooner than expected. Her mother decides to act as if everything were normal so as to spend their best summer ever. Ava confronts the problem in her own way. She steals a big black dog that belongs to a young man on the run...",
        "actors": [
            "Noée Abita",
            "Ava",
            "Juan Cano",
            "Juan",
            "Laure Calamy",
            "Maud",
            "Tamara Cano",
            "Jessica",
            "Ismaël Capelot",
            "",
            "Daouda Diakhaté",
            "Tété",
            "Baptiste Archimbaud",
            "Matthias",
            "Franck Beckmann",
            "L'ophtalmo",
            "Valentine Cadic",
            "Serveuse du mariage"
        ],
        "orig_title": "Ava",
        "status": " Released",
        "orig_lang": " French",
        "budget_x": 3000000.0,
        "revenue": 500000.0,
        "country": "FR"
    },
    {
        "title": "Fractured",
        "date_x": "10/10/2019 ",
        "score": 67.0,
        "genre": [
            "Thriller"
        ],
        "overview": "Driving cross-country, Ray and his wife and daughter stop at a highway rest area where his daughter falls and breaks her arm. After a frantic rush to the hospital and a clash with the check-in nurse, Ray is finally able to get her to a doctor. While the wife and daughter go downstairs for an MRI, Ray, exhausted, passes out in a chair in the lobby. Upon waking up, they have no record or knowledge of Ray's family ever being checked in.",
        "actors": [
            "Sam Worthington",
            "Ray Monroe",
            "Lily Rabe",
            "Joanne Monroe",
            "Stephen Tobolowsky",
            "Dr. Berthram",
            "Adjoa Andoh",
            "Dr. Isaacs",
            "Lauren Cochrane",
            "Officer Childes",
            "Stephanie Sy",
            "Nurse Anne",
            "Chad Bruce",
            "Security Guard Jeff",
            "Derek James Trapp",
            "Organ Orderly #2",
            "Dennis Scullard",
            "Young Father"
        ],
        "orig_title": "Fractured",
        "status": " Released",
        "orig_lang": " English",
        "budget_x": 108200000.0,
        "revenue": 206009040.8,
        "country": "AU"
    },
    {
        "title": "Ralph Breaks the Internet",
        "date_x": "11/26/2018 ",
        "score": 72.0,
        "genre": [
            "Family",
            "Animation",
            "Comedy",
            "Adventure"
        ],
        "overview": "Video game bad guy Ralph and fellow misfit Vanellope von Schweetz must risk it all by traveling to the World Wide Web in search of a replacement part to save Vanellope's video game, Sugar Rush. In way over their heads, Ralph and Vanellope rely on the citizens of the internet — the netizens — to help navigate their way, including an entrepreneur named Yesss, who is the head algorithm and the heart and soul of trend-making site BuzzzTube.",
        "actors": [
            "John C. Reilly",
            "Wreck-It Ralph (voice)",
            "Sarah Silverman",
            "Vanellope von Schweetz (voice)",
            "Gal Gadot",
            "Shank (voice)",
            "Taraji P. Henson",
            "Yesss (voice)",
            "Jack McBrayer",
            "Felix (voice)",
            "Jane Lynch",
            "Calhoun (voice)",
            "Alan Tudyk",
            "KnowsMore (voice)",
            "Alfred Molina",
            "Double Dan / Little Dan (voice)",
            "Ed O'Neill",
            "Mr. Litwak (voice)"
        ],
        "orig_title": "Ralph Breaks the Internet",
        "status": " Released",
        "orig_lang": " English",
        "budget_x": 175000000.0,
        "revenue": 529221154.0,
        "country": "AU"
    },
    {
        "title": "The Proposal",
        "date_x": "06/18/2009 ",
        "score": 71.0,
        "genre": [
            "Comedy",
            "Romance",
            "Drama"
        ],
        "overview": "When she learns she's in danger of losing her visa status and being deported, overbearing book editor Margaret Tate forces her put-upon assistant, Andrew Paxton, to marry her.",
        "actors": [
            "Sandra Bullock",
            "Margaret Tate",
            "Ryan Reynolds",
            "Andrew Paxton",
            "Malin Åkerman",
            "Gertrude",
            "Craig T. Nelson",
            "Joe Paxton",
            "Mary Steenburgen",
            "Grace Paxton",
            "Betty White",
            "Grandma Annie",
            "Denis O'Hare",
            "Mr. Gilbertson",
            "Oscar Nunez",
            "Ramone",
            "Aasif Mandvi",
            "Bob Spaulding"
        ],
        "orig_title": "The Proposal",
        "status": " Released",
        "orig_lang": " English",
        "budget_x": 40000000.0,
        "revenue": 314709717.0,
        "country": "AU"
    },
    {
        "title": "Rampage",
        "date_x": "04/20/2018 ",
        "score": 64.0,
        "genre": [
            "Action",
            "Adventure",
            "Science Fiction"
        ],
        "overview": "Primatologist Davis Okoye shares an unshakable bond with George, the extraordinarily intelligent, silverback gorilla who has been in his care since birth.  But a rogue genetic experiment gone awry mutates this gentle ape into a raging creature of enormous size.  To make matters worse, it’s soon discovered there are other similarly altered animals.  As these newly created alpha predators tear across North America, destroying everything in their path, Okoye teams with a discredited genetic engineer to secure an antidote, fighting his way through an ever-changing battlefield, not only to halt a global catastrophe but to save the fearsome creature that was once his friend.",
        "actors": [
            "Dwayne Johnson",
            "Davis Okoye",
            "Naomie Harris",
            "Dr. Kate Caldwell",
            "Malin Åkerman",
            "Claire Wyden",
            "Jeffrey Dean Morgan",
            "Harvey Russell",
            "Jake Lacy",
            "Brett Wyden",
            "Joe Manganiello",
            "Burke",
            "Marley Shelton",
            "Dr. Kerry Atkins",
            "P.J. Byrne",
            "Nelson",
            "Demetrius Grosse",
            "Colonel Blake"
        ],
        "orig_title": "Rampage",
        "status": " Released",
        "orig_lang": " English",
        "budget_x": 120000000.0,
        "revenue": 427947217.0,
        "country": "AU"
    },
    {
        "title": "Ashfall",
        "date_x": "01/09/2020 ",
        "score": 68.0,
        "genre": [
            "Action",
            "Adventure",
            "Thriller"
        ],
        "overview": "A group of unlikely heroes from across the Korean peninsula try to save the day after a volcano erupts on the mythical and majestic Baekdu Mountain.",
        "actors": [
            "Lee Byung-hun",
            "Lee Jun-pyeong",
            "Ha Jung-woo",
            "Jo In-chang",
            "Ma Dong-seok",
            "Kang Bong-rae",
            "Jeon Hye-jin",
            "Jeon Yu-gyeong",
            "Bae Suzy",
            "Seo Ji-young",
            "Lee Kyung-young",
            "General Choi",
            "Kim Si-a",
            "Sun-ok",
            "Lee Sang-won",
            "Park Tae-sik",
            "Ok Ja-yeon",
            "Sergeant Min"
        ],
        "orig_title": " 백두산",
        "status": " Released",
        "orig_lang": " Korean",
        "budget_x": 17700000.0,
        "revenue": 61321941.0,
        "country": "AU"
    },
    {
        "title": "Wrong Turn",
        "date_x": "02/04/2021 ",
        "score": 60.0,
        "genre": [
            "Horror",
            "Thriller"
        ],
        "overview": "Jen and a group of friends set out to hike the Appalachian Trail. Despite warnings to stick to the trail, the hikers stray off course—and cross into land inhabited by The Foundation, a hidden community of mountain dwellers who use deadly means to protect their way of life.",
        "actors": [
            "Charlotte Vega",
            "Jennifer Shaw",
            "Adain Bradley",
            "Darius Clemons",
            "Bill Sage",
            "John Venable",
            "Emma Dumont",
            "Milla D'Angelo",
            "Dylan McTee",
            "Adam Lucas",
            "Daisy Head",
            "Edith",
            "Matthew Modine",
            "Scott Shaw",
            "Vardaan Arora",
            "Gary Amaan",
            "Adrian Favela",
            "Luis Ortiz"
        ],
        "orig_title": "Wrong Turn",
        "status": " Released",
        "orig_lang": " English",
        "budget_x": 10000000.0,
        "revenue": 28649556.0,
        "country": "AU"
    },
    {
        "title": "Alice in Wonderland",
        "date_x": "07/01/2010 ",
        "score": 66.0,
        "genre": [
            "Family",
            "Fantasy",
            "Adventure"
        ],
        "overview": "Alice, now 19 years old, returns to the whimsical world she first entered as a child and embarks on a journey to discover her true destiny.",
        "actors": [
            "Mia Wasikowska",
            "Alice Kingsleigh",
            "Johnny Depp",
            "The Mad Hatter",
            "Anne Hathaway",
            "The White Queen",
            "Helena Bonham Carter",
            "The Red Queen",
            "Crispin Glover",
            "The Knave of Hearts",
            "Matt Lucas",
            "Tweedledee / Tweedledum",
            "Alan Rickman",
            "The Caterpillar (voice)",
            "Stephen Fry",
            "The Cheshire Cat (voice)",
            "Michael Sheen",
            "The White Rabbit (voice)"
        ],
        "orig_title": "Alice in Wonderland",
        "status": " Released",
        "orig_lang": " English",
        "budget_x": 200000000.0,
        "revenue": 1025491110.0,
        "country": "AU"
    },
    {
        "title": "Alice in Wonderland",
        "date_x": "07/01/2010 ",
        "score": 66.0,
        "genre": [
            "Family",
            "Fantasy",
            "Adventure"
        ],
        "overview": "Alice, now 19 years old, returns to the whimsical world she first entered as a child and embarks on a journey to discover her true destiny.",
        "actors": [
            "Mia Wasikowska",
            "Alice Kingsleigh",
            "Johnny Depp",
            "The Mad Hatter",
            "Anne Hathaway",
            "The White Queen",
            "Helena Bonham Carter",
            "The Red Queen",
            "Crispin Glover",
            "The Knave of Hearts",
            "Matt Lucas",
            "Tweedledee / Tweedledum",
            "Alan Rickman",
            "The Caterpillar (voice)",
            "Stephen Fry",
            "The Cheshire Cat (voice)",
            "Michael Sheen",
            "The White Rabbit (voice)"
        ],
        "orig_title": "Alice in Wonderland",
        "status": " Released",
        "orig_lang": " English",
        "budget_x": 3000000.0,
        "revenue": 0.0,
        "country": "AU"
    },
    {
        "title": "Ripper Untold",
        "date_x": "06/28/2021 ",
        "score": 62.0,
        "genre": [
            "Horror"
        ],
        "overview": "A detective and a medical examiner join forces to solve a series of horrific murders in Victorian London - but one of them harbors a deadly secret.",
        "actors": [
            "Jonathan Hansler",
            "Locque",
            "Phil Molloy",
            "Rees",
            "Dawn Butler",
            "Miss Levine",
            "Chris Bell",
            "Stubb",
            "Sylvia Robson",
            "Elizabeth",
            "Barry Shannon",
            "Lowry",
            "Jacob Anderton",
            "Dodd",
            "Shady Murphy",
            "Sally",
            "Marcus Langford",
            "Constable"
        ],
        "orig_title": "Ripper Untold",
        "status": " Released",
        "orig_lang": " English",
        "budget_x": 80200000.0,
        "revenue": 338842741.4,
        "country": "GB"
    },
    {
        "title": "Rurouni Kenshin: The Beginning",
        "date_x": "06/04/2021 ",
        "score": 77.0,
        "genre": [
            "Action",
            "Adventure",
            "Drama"
        ],
        "overview": "Before he was a protector, Kenshin was a fearsome assassin known as Battosai. But when he meets gentle Tomoe Yukishiro, a beautiful young woman who carries a huge burden in her heart, his life will change forever.",
        "actors": [
            "Takeru Satoh",
            "Kenshin Himura",
            "Kasumi Arimura",
            "Tomoe Yukishiro",
            "Issey Takahashi",
            "Kogoro Katsura",
            "Nijiro Murakami",
            "Soji Okita",
            "Masanobu Ando",
            "Shinsaku Takasugi",
            "Kazuki Kitamura",
            "Tatsumi",
            "Yosuke Eguchi",
            "Hajime Saito",
            "Towa Araki",
            "Enishi Yukishiro",
            "Shima Onishi",
            "Iizuka"
        ],
        "orig_title": " るろうに剣心 最終章 The Beginning",
        "status": " Released",
        "orig_lang": " Japanese",
        "budget_x": 138000000.0,
        "revenue": 450001647.6,
        "country": "JP"
    },
    {
        "title": "Brother Bear",
        "date_x": "12/26/2003 ",
        "score": 73.0,
        "genre": [
            "Adventure",
            "Animation",
            "Family"
        ],
        "overview": "When an impulsive boy named Kenai is magically transformed into a bear, he must literally walk in another's footsteps until he learns some valuable life lessons. His courageous and often zany journey introduces him to a forest full of wildlife, including the lovable bear cub Koda, hilarious moose Rutt and Tuke, woolly mammoths and rambunctious rams.",
        "actors": [
            "Joaquin Phoenix",
            "Kenai (voice)",
            "Jeremy Suarez",
            "Koda (voice)",
            "Jason Raize",
            "Denahi (voice)",
            "Rick Moranis",
            "Rutt (voice)",
            "Dave Thomas",
            "Tuke (voice)",
            "D.B. Sweeney",
            "Sitka (voice)",
            "Joan Copeland",
            "Tanana (voice)",
            "Michael Clarke Duncan",
            "Tug (voice)",
            "Harold Gould",
            "Old Denahi (voice)"
        ],
        "orig_title": "Brother Bear",
        "status": " Released",
        "orig_lang": " English",
        "budget_x": 46000000.0,
        "revenue": 250397798.0,
        "country": "AU"
    },
    {
        "title": "Purple Hearts",
        "date_x": "07/29/2022 ",
        "score": 82.0,
        "genre": [
            "Romance",
            "Drama"
        ],
        "overview": "An aspiring musician agrees to a marriage of convenience with a soon-to-deploy Marine, but a tragedy soon turns their fake relationship all too real.",
        "actors": [
            "Sofia Carson",
            "Cassie Salazar",
            "Nicholas Galitzine",
            "Luke Marrow",
            "John Harlan Kim",
            "Toby",
            "Chosen Jacobs",
            "Frankie",
            "Anthony Ippolito",
            "Johnno",
            "Linden Ashby",
            "Jacob Marrow",
            "Kat Cunning",
            "Nora",
            "Nicholas Duvernay",
            "Armando",
            "Scott Deckert",
            "Jacob Marrow Jr"
        ],
        "orig_title": "Purple Hearts",
        "status": " Released",
        "orig_lang": " English",
        "budget_x": 175200000.0,
        "revenue": 715523713.0,
        "country": "US"
    },
    {
        "title": "Ninja Assassin",
        "date_x": "03/04/2010 ",
        "score": 65.0,
        "genre": [
            "Action",
            "Thriller"
        ],
        "overview": "Ninja Assassin follows Raizo, one of the deadliest assassins in the world. Taken from the streets as a child, he was transformed into a trained killer by the Ozunu Clan, a secret society whose very existence is considered a myth. But haunted by the merciless execution of his friend by the Clan, Raizo breaks free from them and vanishes. Now he waits, preparing to exact his revenge.",
        "actors": [
            "Rain",
            "Raizo",
            "Naomie Harris",
            "Mika Coretti",
            "Sung Kang",
            "Hollywood",
            "Randall Duk Kim",
            "Tattoo Master",
            "Rick Yune",
            "Takeshi",
            "Yuki Iwamoto",
            "Yakuza Couch",
            "Shô Kosugi",
            "Ozunu",
            "Ben Miles",
            "Maslow",
            "Linh-Dan Pham",
            "Pretty Ninja"
        ],
        "orig_title": "Ninja Assassin",
        "status": " Released",
        "orig_lang": " English",
        "budget_x": 50000000.0,
        "revenue": 62209892.0,
        "country": "AU"
    },
    {
        "title": "Presences",
        "date_x": "09/07/2022 ",
        "score": 69.0,
        "genre": [
            "Horror"
        ],
        "overview": "A man who loses his wife and goes to seclude himself in a cabin in the woods, where strange things happen.",
        "actors": [
            "Alberto Ammann",
            "Víctor",
            "Yalitza Aparicio",
            "Paulina",
            "Josué Maychi",
            "",
            "Andrea Santibañez",
            "Alicia",
            "Leo Danse Alos",
            "Almita",
            "Ariel Bonilla",
            "Doctor Juan Esquivel",
            "Analy Castro",
            "Policewoman",
            "Cher Constantine",
            "Dra. Dávila",
            "Adriana Deangelis",
            "Adela"
        ],
        "orig_title": " Presencias",
        "status": " Released",
        "orig_lang": " Spanish, Castilian",
        "budget_x": 101400000.0,
        "revenue": 531683245.8,
        "country": "MX"
    },
    {
        "title": "Miss Peregrine's Home for Peculiar Children",
        "date_x": "09/29/2016 ",
        "score": 68.0,
        "genre": [
            "Fantasy",
            "Adventure",
            "Family",
            "Drama"
        ],
        "overview": "A teenager finds himself transported to an island where he must help protect a group of orphans with special powers from creatures intent on destroying them.",
        "actors": [
            "Eva Green",
            "Miss Peregrine",
            "Asa Butterfield",
            "Jacob Portman",
            "Samuel L. Jackson",
            "Barron",
            "Judi Dench",
            "Miss Avocet",
            "Rupert Everett",
            "Ornithologist",
            "Chris O'Dowd",
            "Franklin Portman",
            "Allison Janney",
            "Dr. Golan",
            "Ella Purnell",
            "Emma Bloom",
            "Terence Stamp",
            "Abraham Portman"
        ],
        "orig_title": "Miss Peregrine's Home for Peculiar Children",
        "status": " Released",
        "orig_lang": " English",
        "budget_x": 110000000.0,
        "revenue": 296482446.0,
        "country": "AU"
    },
    {
        "title": "How to Train Your Dragon",
        "date_x": "03/25/2010 ",
        "score": 78.0,
        "genre": [
            "Fantasy",
            "Adventure",
            "Animation",
            "Family"
        ],
        "overview": "As the son of a Viking leader on the cusp of manhood, shy Hiccup Horrendous Haddock III faces a rite of passage: he must kill a dragon to prove his warrior mettle. But after downing a feared dragon, he realizes that he no longer wants to destroy it, and instead befriends the beast – which he names Toothless – much to the chagrin of his warrior father.",
        "actors": [
            "Jay Baruchel",
            "Hiccup  Horrendous Haddock III (voice)",
            "Gerard Butler",
            "Stoick the Vast (voice)",
            "Craig Ferguson",
            "Gobber the Belch (voice)",
            "America Ferrera",
            "Astrid Hofferson (voice)",
            "Jonah Hill",
            "Snotlout Jorgenson (voice)",
            "Christopher Mintz-Plasse",
            "Fishlegs Ingerman (voice)",
            "T.J. Miller",
            "Tuffnut Thorston (voice)",
            "Kristen Wiig",
            "Ruffnut Thorston (voice)",
            "David Tennant",
            "Spitelout (voice)"
        ],
        "orig_title": "How to Train Your Dragon",
        "status": " Released",
        "orig_lang": " English",
        "budget_x": 165000000.0,
        "revenue": 494870992.0,
        "country": "AU"
    },
    {
        "title": "Scream 3",
        "date_x": "03/23/2000 ",
        "score": 60.0,
        "genre": [
            "Horror",
            "Mystery"
        ],
        "overview": "While Sidney lives in safely guarded seclusion, bodies begin dropping around the Hollywood set of STAB 3, the latest movie based on the gruesome Woodsboro killings.",
        "actors": [
            "David Arquette",
            "Dewey Riley",
            "Neve Campbell",
            "Sidney Prescott",
            "Courteney Cox",
            "Gale Weathers",
            "Patrick Dempsey",
            "Mark Kincaid",
            "Scott Foley",
            "Roman Bridger",
            "Lance Henriksen",
            "John Milton",
            "Matt Keeslar",
            "Tom Prinze",
            "Jenny McCarthy-Wahlberg",
            "Sarah Darling",
            "Emily Mortimer",
            "Angelina Tyler"
        ],
        "orig_title": "Scream 3",
        "status": " Released",
        "orig_lang": " English",
        "budget_x": 40000000.0,
        "revenue": 161838076.0,
        "country": "AU"
    },
    {
        "title": "Predator",
        "date_x": "08/20/1987 ",
        "score": 75.0,
        "genre": [
            "Science Fiction",
            "Action",
            "Adventure",
            "Thriller"
        ],
        "overview": "A team of elite commandos on a secret mission in a Central American jungle come to find themselves hunted by an extraterrestrial warrior.",
        "actors": [
            "Arnold Schwarzenegger",
            "Major Alan \"Dutch\" Schaefer",
            "Carl Weathers",
            "Al Dillon",
            "Elpidia Carrillo",
            "Anna Gonsalves",
            "Jesse Ventura",
            "Blain Cooper",
            "Sonny Landham",
            "Billy Sole",
            "Bill Duke",
            "Mac Eliot",
            "Richard Chaves",
            "Jorge \"Poncho\" Ramirez",
            "R. G. Armstrong",
            "Major General Homer Phillips",
            "Shane Black",
            "Rick Hawkins"
        ],
        "orig_title": "Predator",
        "status": " Released",
        "orig_lang": " English",
        "budget_x": 18000000.0,
        "revenue": 98267558.0,
        "country": "AU"
    },
    {
        "title": "Superman/Shazam!: The Return of Black Adam",
        "date_x": "11/09/2010 ",
        "score": 71.0,
        "genre": [
            "Animation",
            "Action"
        ],
        "overview": "Chosen the world’s protector against the Seven Deadly Enemies of Man – pride, envy, greed, hatred, selfishness, laziness and injustice – young Billy Batson accepts his destiny as Captain Marvel. Battling alongside Superman against nefarious Black Adam, Billy soon discovers the challenge super heroes ultimately face: is it revenge or justice?",
        "actors": [
            "George Newbern",
            "Kal-El / Clark Kent / Superman (voice)",
            "Jerry O'Connell",
            "Captain Marvel (voice)",
            "Arnold Vosloo",
            "Black Adam (voice)",
            "Zach Callison",
            "Billy Batson (voice)",
            "James Garner",
            "Shazam (voice)",
            "Kevin Michael Richardson",
            "Mister Tawky Tawny (voice)",
            "Danica McKellar",
            "Sally (voice)",
            "Josh Keaton",
            "Punk (voice)"
        ],
        "orig_title": "Superman/Shazam!: The Return of Black Adam",
        "status": " Released",
        "orig_lang": " English",
        "budget_x": 61095923.8,
        "revenue": 470754235.2,
        "country": "US"
    },
    {
        "title": "L'oubliée d'Amboise",
        "date_x": "06/25/2022 ",
        "score": 66.0,
        "genre": [
            "Crime",
            "TV Movie"
        ],
        "overview": "A violinist is found dead not far from the tomb of DaVinci, in a suspicious position. Captain of the Orléans research section, Alban Dutertre teams up with Officer Bérénice Amarillo. Alban and Bérénice will have to solve the puzzle.",
        "actors": [
            "Philippe Bas",
            "Alban Dutertre",
            "Pauline Bression",
            "Bérénice",
            "Édouard Montoute",
            "Patrice",
            "François-Eric Gendron",
            "Louis",
            "Jean-Marie Winling",
            "Charles Dutertre",
            "Lucia Passaniti",
            "Lisa Pasquier",
            "Olivier Chantreau",
            "Léo",
            "Anton Rival",
            "Amaury",
            "Agathe de La Boulaye",
            "Nicole"
        ],
        "orig_title": "L'oubliée d'Amboise",
        "status": " Released",
        "orig_lang": " French",
        "budget_x": 90800000.0,
        "revenue": 389307031.4,
        "country": "FR"
    },
    {
        "title": "Ponyo",
        "date_x": "07/06/2009 ",
        "score": 77.0,
        "genre": [
            "Animation",
            "Fantasy",
            "Family"
        ],
        "overview": "From the legendary Studio Ghibli, creators of Spirited Away and My Neighbor Totoro, and Academy Award®-winning director Hayao Miyazaki, comes a heartwarming adventure. When Sosuke, a young boy who lives on a clifftop overlooking the sea, rescues a stranded goldfish named Ponyo, he discovers more than he bargained for. Ponyo is a curious, energetic young creature who yearns to be human, but even as she causes chaos around the house, her father, a powerful sorcerer, schemes to return Ponyo to the sea.",
        "actors": [
            "Yuria Kozuki",
            "Ponyo (voice)",
            "Hiroki Doi",
            "Sosuke (voice)",
            "George Tokoro",
            "Fujimoto (voice)",
            "Tomoko Yamaguchi",
            "Risa (voice)",
            "Yuki Amami",
            "Gran Mamare (voice)",
            "Kazushige Nagashima",
            "Koichi (voice)",
            "Akiko Yano",
            "Ponyo's Sister (voice)",
            "Shinichi Hatori",
            "Anchorman (voice)",
            "Tokie Hidari",
            "Kayo (voice)"
        ],
        "orig_title": " 崖の上のポニョ",
        "status": " Released",
        "orig_lang": " Japanese",
        "budget_x": 41677699.0,
        "revenue": 202404009.0,
        "country": "AU"
    },
    {
        "title": "Snake Eyes: G.I. Joe Origins",
        "date_x": "07/22/2021 ",
        "score": 66.0,
        "genre": [
            "Action",
            "Adventure"
        ],
        "overview": "After saving the life of their heir apparent, tenacious loner Snake Eyes is welcomed into an ancient Japanese clan called the Arashikage where he is taught the ways of the ninja warrior. But, when secrets from his past are revealed, Snake Eyes' honor and allegiance will be tested – even if that means losing the trust of those closest to him.",
        "actors": [
            "Henry Golding",
            "Snake Eyes",
            "Andrew Koji",
            "Tommy / Storm Shadow",
            "Haruka Abe",
            "Akiko",
            "Úrsula Corberó",
            "The Baroness",
            "Samara Weaving",
            "Scarlett",
            "Takehiro Hira",
            "Kenta",
            "Eri Ishida",
            "Sen",
            "Iko Uwais",
            "Hard Master",
            "Peter Mensah",
            "Blind Master"
        ],
        "orig_title": "Snake Eyes: G.I. Joe Origins",
        "status": " Released",
        "orig_lang": " English",
        "budget_x": 88000000.0,
        "revenue": 34677221.0,
        "country": "AU"
    },
    {
        "title": "Knights of the Zodiac",
        "date_x": "04/28/2023 ",
        "score": 0.0,
        "genre": [
            "Fantasy",
            "Action",
            "Adventure"
        ],
        "overview": "When a headstrong street orphan, Seiya, in search of his abducted sister unwittingly taps into hidden powers, he discovers he might be the only person alive who can protect a reincarnated goddess, sent to watch over humanity. Can he let his past go and embrace his destiny to become a Knight of the Zodiac?",
        "actors": [
            "Mackenyu",
            "Seiya",
            "Famke Janssen",
            "Guraad",
            "Madison Iseman",
            "Sienna",
            "Diego Tinoco",
            "Nero",
            "Mark Dacascos",
            "Mylock",
            "Nick Stahl",
            "Cassius",
            "Sean Bean",
            "Alman Kido",
            "Godfrey Gao",
            "",
            "Caitlin M Hutson",
            "Marin"
        ],
        "orig_title": "Knights of the Zodiac",
        "status": " Post Production",
        "orig_lang": " English",
        "budget_x": 264940000.0,
        "revenue": 175269998.8,
        "country": "JP"
    },
    {
        "title": "Dragon Ball Z: Cooler's Revenge",
        "date_x": "07/20/1991 ",
        "score": 69.0,
        "genre": [
            "Action",
            "Animation",
            "Science Fiction"
        ],
        "overview": "After defeating Frieza, Goku returns to Earth and goes on a camping trip with Gohan and Krillin. Everything is normal until Cooler - Frieza's brother - sends three henchmen after Goku. A long fight ensues between our heroes and Cooler, in which he transforms into the fourth stage of his evolution and has the edge in the fight... until Goku transforms into a Super Saiyan.",
        "actors": [
            "Masako Nozawa",
            "Son Gokû / Son Gohan / Bardock (voice)",
            "Toshio Furukawa",
            "Piccolo (voice)",
            "Mayumi Tanaka",
            "Kuririn / Yajirobe (voice)",
            "Naoki Tatsuta",
            "Oolong / Haiya Dragon (voice)",
            "Naoko Watanabe",
            "Chichi (voice)",
            "Kōhei Miyauchi",
            "Kame Sen'nin (voice)",
            "Ichiro Nagai",
            "Karin (voice)",
            "Ryusei Nakao",
            "Coola / Freeza (voice)",
            "Show Hayami",
            "Sauzer (voice)"
        ],
        "orig_title": " ドラゴンボールZ とびっきりの最強対最強",
        "status": " Released",
        "orig_lang": " Japanese",
        "budget_x": 27104689.8,
        "revenue": 16331742.0,
        "country": "JP"
    },
    {
        "title": "My Sweet Monster",
        "date_x": "06/23/2022 ",
        "score": 65.0,
        "genre": [
            "Animation",
            "Adventure",
            "Family"
        ],
        "overview": "A scandal in the royal family: the wayward princess Barbara escaped from the palace and went through the forest in search of a handsome prince. However, instead of the cherished meeting with her beloved, she is captured by Buka, the most dangerous robber of the kingdom. But it quickly becomes clear that the brisk princess is ready to turn Buka's life into a nightmare, just to reach her goal. So the restless Varvara begins to establish her own order in the forest.",
        "actors": [
            "Lyubov Aksyonova",
            "Varvara (voice)",
            "Aleksey Chumakov",
            "Buka (voice)",
            "Alena Doletskaya",
            "Edwardine",
            "princess (voice)",
            "Timur Kerimov",
            "Rabbit (voice)",
            "Prokhor Chekhovskoy",
            "Shishek (voice)",
            "Vladislav Kopp",
            "Stepan (voice)",
            "Pyotr Ivaschenko",
            "Vasiliy (voice)"
        ],
        "orig_title": " Бука. Моё любимое чудище",
        "status": " Released",
        "orig_lang": " Russian",
        "budget_x": 111800000.0,
        "revenue": 589285934.8,
        "country": "AU"
    },
    {
        "title": "All the Places",
        "date_x": "02/14/2023 ",
        "score": 67.0,
        "genre": [
            "Comedy",
            "Drama"
        ],
        "overview": "Two siblings who haven't seen each other in 15 years mend their relationship while fulfilling a childhood dream: a motorcycle road trip through Mexico.",
        "actors": [
            "Mauricio Ochmann",
            "",
            "Ana Serradilla",
            "Gabriela",
            "David Chocarro",
            "Lalo",
            "Diana Bovio",
            "Tania",
            "Irán Castillo",
            "Elena",
            "Ana Claudia Talancón",
            "Mama Fer y Gabo"
        ],
        "orig_title": " A Todas Partes",
        "status": " Released",
        "orig_lang": " Spanish, Castilian",
        "budget_x": 64200000.0,
        "revenue": 252076159.2,
        "country": "MX"
    },
    {
        "title": "Beauty and the Beast",
        "date_x": "03/23/2017 ",
        "score": 70.0,
        "genre": [
            "Family",
            "Fantasy",
            "Romance"
        ],
        "overview": "A live-action adaptation of Disney's version of the classic tale of a cursed prince and a beautiful young woman who helps him break the spell.",
        "actors": [
            "Emma Watson",
            "Belle",
            "Dan Stevens",
            "Beast",
            "Luke Evans",
            "Gaston",
            "Josh Gad",
            "LeFou",
            "Kevin Kline",
            "Maurice",
            "Hattie Morahan",
            "Agathe / Enchantress",
            "Haydn Gwynne",
            "Clothilde",
            "Gerard Horan",
            "Jean the Potter",
            "Ray Fearon",
            "Père Robert"
        ],
        "orig_title": "Beauty and the Beast",
        "status": " Released",
        "orig_lang": " English",
        "budget_x": 160000000.0,
        "revenue": 1268697483.0,
        "country": "AU"
    },
    {
        "title": "Beauty and the Beast",
        "date_x": "03/23/2017 ",
        "score": 70.0,
        "genre": [
            "Family",
            "Fantasy",
            "Romance"
        ],
        "overview": "A live-action adaptation of Disney's version of the classic tale of a cursed prince and a beautiful young woman who helps him break the spell.",
        "actors": [
            "Emma Watson",
            "Belle",
            "Dan Stevens",
            "Beast",
            "Luke Evans",
            "Gaston",
            "Josh Gad",
            "LeFou",
            "Kevin Kline",
            "Maurice",
            "Hattie Morahan",
            "Agathe / Enchantress",
            "Haydn Gwynne",
            "Clothilde",
            "Gerard Horan",
            "Jean the Potter",
            "Ray Fearon",
            "Père Robert"
        ],
        "orig_title": "Beauty and the Beast",
        "status": " Released",
        "orig_lang": " English",
        "budget_x": 20000000.0,
        "revenue": 438656843.0,
        "country": "AU"
    },
    {
        "title": "Hunting Ava Bravo",
        "date_x": "04/01/2022 ",
        "score": 64.0,
        "genre": [
            "Thriller",
            "Action"
        ],
        "overview": "Billionaire sportsman Buddy King unwinds by hunting human captives on his remote mountain estate. But his latest victim, Ava Bravo, is no easy target.",
        "actors": [
            "Kate del Castillo",
            "Ava Bravo",
            "Marc Blucas",
            "Buddy King",
            "Julio Lazarte",
            "Antonio",
            "Halem Medina",
            "The Stranger",
            "Bryce Fernelius",
            "Jose"
        ],
        "orig_title": "Hunting Ava Bravo",
        "status": " Released",
        "orig_lang": " English",
        "budget_x": 75600000.0,
        "revenue": 365470598.0,
        "country": "US"
    },
    {
        "title": "Marudase Kintarou",
        "date_x": "12/11/2020 ",
        "score": 63.0,
        "genre": [
            "Romance",
            "Comedy",
            "Animation"
        ],
        "overview": "Makoto's grandfather was the principal of the great Onodera Academy, and when he passed away, he left Makoto and his school staff with one very important will - \"The one man who is able to seduce Makoto with his superb sexual techniques will be given the right to take over as Onodera Academy's new principal!\" Because of this ridiculous last request, Makoto is now every faculty member's target for sexual harassment! Desperate to protect his virginity, Makoto seeks help from his childhood friend (and the man who he has always loved), Kintaro.",
        "actors": [
            "Wataru Hatano",
            "Inukai (voice)",
            "Takuma Terashima",
            "Momotarō Naraba (voice)",
            "Toshiyuki Morikawa",
            "Marudase Kintarou (voice)",
            "Soma Saito",
            "Makoto Onodera (voice)",
            "Katsumi Fukuhara",
            "Kijitani (voice)",
            "Shota Hayama",
            "Saruwatari (voice)"
        ],
        "orig_title": " まるだせ金太狼",
        "status": " Released",
        "orig_lang": " Japanese",
        "budget_x": 162940000.0,
        "revenue": 890454742.6,
        "country": "JP"
    },
    {
        "title": "Drag Me to Hell",
        "date_x": "03/15/2009 ",
        "score": 64.0,
        "genre": [
            "Horror",
            "Thriller"
        ],
        "overview": "After denying a woman the extension she needs to keep her home, loan officer Christine Brown sees her once-promising life take a startling turn for the worse. Christine is convinced she's been cursed by a Gypsy, but her boyfriend is skeptical. Her only hope seems to lie in a psychic who claims he can help her lift the curse and keep her soul from being dragged straight to hell.",
        "actors": [
            "Alison Lohman",
            "Christine Brown",
            "Justin Long",
            "Clay Dalton",
            "Lorna Raver",
            "Mrs. Ganush",
            "Dileep Rao",
            "Rham Jas",
            "David Paymer",
            "Mr. Jacks",
            "Adriana Barraza",
            "Shaun San Dena",
            "Chelcie Ross",
            "Leonard Dalton",
            "Reggie Lee",
            "Stu Rubin",
            "Molly Cheek",
            "Trudy Dalton"
        ],
        "orig_title": "Drag Me to Hell",
        "status": " Released",
        "orig_lang": " English",
        "budget_x": 30000000.0,
        "revenue": 90810892.0,
        "country": "US"
    },
    {
        "title": "Brian Banks",
        "date_x": "08/09/2019 ",
        "score": 73.0,
        "genre": [
            "Drama"
        ],
        "overview": "An All-American football player's dreams to play in the NFL are halted when he is falsely accused of rape and sent to prison.",
        "actors": [
            "Aldis Hodge",
            "Brian Banks",
            "Greg Kinnear",
            "Justin Brooks",
            "Tiffany Dupont",
            "Alissa Bjerkhoel",
            "Sherri Shepherd",
            "Leomia",
            "Melanie Liburd",
            "Karina",
            "Dorian Missick",
            "Mick Randolph",
            "Xosha Roquemore",
            "Kennisha Rice",
            "Matt Battaglia",
            "Pete Carroll",
            "Jose Miguel Vasquez",
            "District Attorney Mateo"
        ],
        "orig_title": "Brian Banks",
        "status": " Released",
        "orig_lang": " English",
        "budget_x": 10000000.0,
        "revenue": 4376820.0,
        "country": "US"
    },
    {
        "title": "Bullet Proof",
        "date_x": "08/19/2022 ",
        "score": 58.0,
        "genre": [
            "Action",
            "Crime"
        ],
        "overview": "The Thief  pulls off the robbery of a lifetime when he robs the psychotic drug lord, Temple. The plan goes off without a hitch until the Thief discovers a stowaway in his getaway car - Temple's pregnant wife, Mia.",
        "actors": [
            "Vinnie Jones",
            "Temple",
            "Lina Lecompte",
            "Mia",
            "James Clayton",
            "The Thief",
            "Janvier Katabarwa",
            "The Frenchman",
            "Danny Mac",
            "Skinny",
            "Glenn Ennis",
            "Griz",
            "Philip Granger",
            "Vic",
            "Lori Triolo",
            "Dr Zimmerman"
        ],
        "orig_title": "Bullet Proof",
        "status": " Released",
        "orig_lang": " English",
        "budget_x": 54200000.0,
        "revenue": 252564447.8,
        "country": "US"
    },
    {
        "title": "Beautiful Disaster",
        "date_x": "04/12/2023 ",
        "score": 59.0,
        "genre": [
            "Romance",
            "Drama",
            "Comedy"
        ],
        "overview": "Bad-boy Travis is exactly what college freshman Abby needs and wants to avoid. He spends his nights fighting in underground boxing matches, and his days as the ultimate college campus charmer. But Abby wants nothing to do with Travis. Intrigued by Abby’s resistance, Travis offers her a simple bet: if he loses his next fight, he must remain sex-free for a month. If he wins, Abby must live in his apartment for the same amount of time. Either way, Travis has no idea that Abby’s dark past is about to emerge, and he may have finally met his match.",
        "actors": [
            "Dylan Sprouse",
            "Travis Maddox",
            "Virginia Gardner",
            "Abby Abernathy",
            "Austin North",
            "Shepley Maddox",
            "Libe Barer",
            "America Mason",
            "Rob Estes",
            "Benny",
            "Brian Austin Green",
            "Mick Abernathy",
            "Autumn Reeser",
            "Professor Felder",
            "Samuel Larsen",
            "Jesse Viveros",
            "Manal El-Feitury",
            "Bursa"
        ],
        "orig_title": "Beautiful Disaster",
        "status": " Released",
        "orig_lang": " English",
        "budget_x": 94800000.0,
        "revenue": 809767733.4,
        "country": "US"
    },
    {
        "title": "Sniper: Rogue Mission",
        "date_x": "08/16/2022 ",
        "score": 66.0,
        "genre": [
            "Action",
            "Thriller",
            "Mystery"
        ],
        "overview": "When a crooked federal agent is involved in a human sex trafficking ring, Sniper and CIA Rookie Brandon Beckett goes rogue, teaming up with his former allies Homeland Security Agent Zero and assassin Lady Death to uncover the corrupt agent and take down the criminal organization.",
        "actors": [
            "Chad Michael Collins",
            "Brandon Beckett",
            "Ryan Robbins",
            "Agent Zeke 'Zero' Rosenberg",
            "Sayaka Akimoto",
            "Lady Death",
            "Josh Brener",
            "",
            "Dennis Haysbert",
            "Colonel",
            "Brendan Sexton III",
            "Gildie",
            "Jocelyn Hudon",
            "Mary Jane",
            "CindyMarie Small",
            "Shelly Gorfein",
            "Solange Sookram",
            "French Maid Cam Girl"
        ],
        "orig_title": "Sniper: Rogue Mission",
        "status": " Released",
        "orig_lang": " English",
        "budget_x": 121000000.0,
        "revenue": 338580387.8,
        "country": "US"
    },
    {
        "title": "Gladiator",
        "date_x": "05/04/2000 ",
        "score": 82.0,
        "genre": [
            "Action",
            "Drama",
            "Adventure"
        ],
        "overview": "In the year 180, the death of emperor Marcus Aurelius throws the Roman Empire into chaos.  Maximus is one of the Roman army's most capable and trusted generals and a key advisor to the emperor.  As Marcus' devious son Commodus ascends to the throne, Maximus is set to be executed.  He escapes, but is captured by slave traders.  Renamed Spaniard and forced to become a gladiator, Maximus must battle to the death with other men for the amusement of paying audiences.",
        "actors": [
            "Russell Crowe",
            "Maximus Meridius",
            "Joaquin Phoenix",
            "Emperor Commodus",
            "Connie Nielsen",
            "Lucilla",
            "Oliver Reed",
            "Proximo",
            "Richard Harris",
            "Marcus Aurelius",
            "Derek Jacobi",
            "Gracchus",
            "Djimon Hounsou",
            "Juba",
            "David Schofield",
            "Falco",
            "John Shrapnel",
            "Gaius"
        ],
        "orig_title": "Gladiator",
        "status": " Released",
        "orig_lang": " English",
        "budget_x": 103000000.0,
        "revenue": 452282115.0,
        "country": "AU"
    },
    {
        "title": "The Reading",
        "date_x": "02/02/2023 ",
        "score": 74.0,
        "genre": [
            "Drama",
            "Thriller"
        ],
        "overview": "After a deadly home invasion, Emma (Mo'Nique Hicks) copes by writing a book, but when a young psychic and her team perform a reading in her home, a new terror is unleashed.",
        "actors": [
            "Mo'Nique",
            "Emma Leeden",
            "Chasity Sereal",
            "Sky Brown",
            "Denisha Hardeman",
            "Jessie",
            "Ian Haywood",
            "Gregory",
            "Mcauley Teters",
            "Randy",
            "Lisa Alavi",
            "Ashley Leeden",
            "Charnele Brown",
            "Oda Brown",
            "Cooper Helm",
            "Mathew Leeden",
            "Sara Alavi",
            "Rachel Gates"
        ],
        "orig_title": "The Reading",
        "status": " Released",
        "orig_lang": " English",
        "budget_x": 124000000.0,
        "revenue": 778605895.4,
        "country": "US"
    }
]